pilibre/__init__.py
pilibre/__main__.py
pilibre/_theme.py
pilibre/config/__init__.py
pilibre/config/files.py
pilibre/console.py
pilibre/graph/__init__.py
pilibre/graph/meter.py
pilibre/main.py
pilibre/screensaver/__init__.py
pilibre/screensaver/_background.py
pilibre/screensaver/_center.py
pilibre/screensaver/_clock.py
pilibre/screensaver/_logo.py
pilibre/screensaver/screensaver.py
pilibre-0.1.0.dist-info/WHEEL
pilibre-0.1.0.dist-info/entry_points.txt
pilibre-0.1.0.dist-info/LICENSE.txt
pilibre-0.1.0.dist-info/METADATA
pilibre-0.1.0.dist-info/RECORD
