Metadata-Version: 2.1
Name: pilibre
Version: 0.1.0
Summary: Display hardware metrics from LibreHardwareMonitor, intended to be run on a small screen on a RaspberryPi.
Home-page: https://github.com/acbuie/pilibre
License: MIT
Author: acbuie
Author-email: aidancbuie@gmail.com
Requires-Python: >=3.11,<4.0
Classifier: Development Status :: 1 - Planning
Classifier: Environment :: Console
Classifier: Intended Audience :: End Users/Desktop
Classifier: License :: OSI Approved :: MIT License
Classifier: Natural Language :: English
Classifier: Programming Language :: Python :: 3
Classifier: Programming Language :: Python :: 3.11
Classifier: Programming Language :: Python :: 3.11
Classifier: Topic :: System :: Hardware
Classifier: Topic :: System :: Monitoring
Classifier: Topic :: Terminals
Classifier: Typing :: Typed
Requires-Dist: httpx (>=0.23.3,<0.24.0)
Requires-Dist: rich (>=13.0.1,<14.0.0)
Project-URL: Repository, https://github.com/acbuie/pilibre
